eaas/__init__.py
eaas/eaas.py
eaas/api/__init__.py
eaas/api/liveness.py
pyeaas-0.1.3.dist-info/METADATA
pyeaas-0.1.3.dist-info/WHEEL
pyeaas-0.1.3.dist-info/top_level.txt
pyeaas-0.1.3.dist-info/RECORD
