Metadata-Version: 2.1
Name: pyeaas
Version: 0.1.3
Summary: Build your e-commerce
Home-page: https://github.com/ciulene/eaas
Author: Giuliano Errico
Author-email: errgioul2@gmail.com
Classifier: Programming Language :: Python :: 3
Classifier: License :: OSI Approved :: MIT License
Classifier: Operating System :: OS Independent
Requires-Python: >=3.6
Requires-Dist: aniso8601==9.0.1
Requires-Dist: attrs==24.2.0
Requires-Dist: blinker==1.9.0
Requires-Dist: click==8.1.7
Requires-Dist: Flask==3.1.0
Requires-Dist: Flask-Cors==5.0.0
Requires-Dist: flask-restx==1.3.0
Requires-Dist: gunicorn==23.0.0
Requires-Dist: importlib_resources==6.4.5
Requires-Dist: itsdangerous==2.2.0
Requires-Dist: Jinja2==3.1.4
Requires-Dist: jsonschema==4.23.0
Requires-Dist: jsonschema-specifications==2024.10.1
Requires-Dist: MarkupSafe==3.0.2
Requires-Dist: packaging==24.2
Requires-Dist: pytz==2024.2
Requires-Dist: referencing==0.35.1
Requires-Dist: rpds-py==0.22.3
Requires-Dist: setuptools==75.6.0
Requires-Dist: Werkzeug==3.1.3
Requires-Dist: wheel==0.45.1
